{
    "fixtures": [
        {
	  "game_id": "001",
	  "home_team": "COT",
	  "away_team": "CAR",
	  "game_date": "2024-12-14T23:30:00",
	  "game_timezone": "Europe/London"
	},
	    {
	  "game_id": "002",
	  "home_team": "COV",
	  "away_team": "COV",
	  "game_date": "2024-12-22T20:45:00",
	  "game_timezone": "Europe/London"
	},
	{
	  "game_id": "003",
	  "home_team": "LEE",
	  "away_team": "COV",
	  "game_date": "2025-01-04T22:00:00",
	  "game_timezone": "Europe/London"
	}    
]
}
		
